scrapy_patterns/__init__.py
scrapy_patterns/request_factory.py
scrapy_patterns/site_structure.py
scrapy_patterns/spiderlings/__init__.py
scrapy_patterns/spiderlings/site_pager.py
scrapy_patterns/spiderlings/site_structure_discoverer.py
scrapy_patterns/spiders/__init__.py
scrapy_patterns/spiders/category_based_spider.py
scrapy_patterns/spiders/private/__init__.py
scrapy_patterns/spiders/private/category_based_spider_state.py
tests/__init__.py
tests/test_category_based_spider.py
tests/test_category_based_spider_state.py
tests/test_request_factory.py
tests/test_site_pager.py
tests/test_site_structure.py
tests/test_site_structure_discoverer.py
scrapy_patterns-1.0.2.dist-info/LICENSE
scrapy_patterns-1.0.2.dist-info/METADATA
scrapy_patterns-1.0.2.dist-info/WHEEL
scrapy_patterns-1.0.2.dist-info/top_level.txt
scrapy_patterns-1.0.2.dist-info/RECORD
