Metadata-Version: 2.1
Name: scrapy-patterns
Version: 1.0.2
Summary: Scrapy Patterns
Home-page: https://github.com/oliverdozsa/scrapy-patterns
Author: oliverdozsa
Author-email: dozsa.oliver@gmail.com
License: UNKNOWN
Platform: UNKNOWN
Requires-Dist: scrapy (>=1.0.0)
